tap_clerk/__init__.py
tap_clerk/__main__.py
tap_clerk/client.py
tap_clerk/schemas/__init__.py
tap_clerk/streams.py
tap_clerk/tap.py
tap_clerk-0.0.2.dist-info/LICENSE
tap_clerk-0.0.2.dist-info/METADATA
tap_clerk-0.0.2.dist-info/WHEEL
tap_clerk-0.0.2.dist-info/entry_points.txt
tap_clerk-0.0.2.dist-info/RECORD
