Metadata-Version: 2.1
Name: tap-clerk
Version: 0.0.2
Summary: `tap-clerk` is a Singer tap for Clerk, built with the Meltano Singer SDK.
License: Apache-2.0
Keywords: ELT,Clerk
Author: Panos Papageorgiou
Author-email: panos.papageorgiou@keragon.com
Requires-Python: >=3.10,<4.0
Classifier: Intended Audience :: Developers
Classifier: License :: OSI Approved :: Apache Software License
Classifier: Operating System :: OS Independent
Classifier: Programming Language :: Python :: 3
Classifier: Programming Language :: Python :: 3.10
Classifier: Programming Language :: Python :: 3.11
Classifier: Programming Language :: Python :: 3.12
Classifier: Programming Language :: Python :: 3.8
Classifier: Programming Language :: Python :: 3.9
Provides-Extra: s3
Requires-Dist: fs-s3fs (>=1.1.1,<1.2.0) ; extra == "s3"
Requires-Dist: importlib-resources (==6.1.*) ; python_version < "3.9"
Requires-Dist: requests (>=2.31.0,<2.32.0)
Requires-Dist: singer-sdk (>=0.37.0,<0.38.0)
